MANIFEST.in
README.rst
setup.py
shopify_scraper/__init__.py
shopify_scraper/scraper.py
shopify_scraper.egg-info/PKG-INFO
shopify_scraper.egg-info/SOURCES.txt
shopify_scraper.egg-info/dependency_links.txt
shopify_scraper.egg-info/not-zip-safe
shopify_scraper.egg-info/requires.txt
shopify_scraper.egg-info/top_level.txt