Metadata-Version: 1.0
Name: shopify-scraper
Version: 0.1
Summary: Shopify Reviews Scraper
Home-page: https://github.com/danielfv/shopify_review_scraper
Author: Daniel Valverde
Author-email: danielfvalverde@gmail.com
License: MIT
Keywords: shopify,scraper,review
Platform: UNKNOWN
